LICENSE
MANIFEST.in
README.rst
setup.py
make_qt_ui/__init__.py
make_qt_ui/converter.py
make_qt_ui.egg-info/PKG-INFO
make_qt_ui.egg-info/SOURCES.txt
make_qt_ui.egg-info/dependency_links.txt
make_qt_ui.egg-info/entry_points.txt
make_qt_ui.egg-info/top_level.txt