Metadata-Version: 1.1
Name: make-qt-ui
Version: 0.1.0
Summary: Scripts to simplify conversion of *.ui and *.qrc files to Python
Home-page: https://github.com/reclosedev/make_qt_ui
Author: Roman Haritonov
Author-email: reclosedev@gmail.com
License: BSD License
Keywords: qt,pyside,pyqt
Platform: UNKNOWN
Classifier: License :: OSI Approved :: BSD License
Classifier: Development Status :: 4 - Beta
Classifier: Intended Audience :: Developers
Classifier: Topic :: Software Development :: Libraries :: Python Modules
Classifier: Programming Language :: Python
Classifier: Programming Language :: Python :: 2.7
Classifier: Programming Language :: Python :: 3
